alipayplusmcp/__init__.py
alipayplusmcp/main.py
alipayplusmcp/server.py
alipayplusmcp/sdk/__init__.py
alipayplusmcp/sdk/default_alipay_client.py
alipayplusmcp/sdk/exception/__init__.py
alipayplusmcp/sdk/exception/exception.py
alipayplusmcp/sdk/model/AlipayPlusPathConstant.py
alipayplusmcp/sdk/model/__init__.py
alipayplusmcp/sdk/model/address.py
alipayplusmcp/sdk/model/amount.py
alipayplusmcp/sdk/model/attachment.py
alipayplusmcp/sdk/model/buyer.py
alipayplusmcp/sdk/model/capture_mode.py
alipayplusmcp/sdk/model/certificate.py
alipayplusmcp/sdk/model/customs_info.py
alipayplusmcp/sdk/model/declaration_record.py
alipayplusmcp/sdk/model/env.py
alipayplusmcp/sdk/model/goods.py
alipayplusmcp/sdk/model/http_method.py
alipayplusmcp/sdk/model/in_store_payment_scenario.py
alipayplusmcp/sdk/model/merchant.py
alipayplusmcp/sdk/model/merchant_customs_info.py
alipayplusmcp/sdk/model/order.py
alipayplusmcp/sdk/model/order_status.py
alipayplusmcp/sdk/model/os_type.py
alipayplusmcp/sdk/model/payment_factor.py
alipayplusmcp/sdk/model/payment_method.py
alipayplusmcp/sdk/model/presentment_mode.py
alipayplusmcp/sdk/model/proof_of_delivery.py
alipayplusmcp/sdk/model/quote.py
alipayplusmcp/sdk/model/settlement_strategy.py
alipayplusmcp/sdk/model/shipping.py
alipayplusmcp/sdk/model/terminal_type.py
alipayplusmcp/sdk/model/transaction.py
alipayplusmcp/sdk/model/transaction_receipt.py
alipayplusmcp/sdk/model/transaction_status_type.py
alipayplusmcp/sdk/model/transaction_type.py
alipayplusmcp/sdk/model/user_name.py
alipayplusmcp/sdk/net/__init__.py
alipayplusmcp/sdk/net/default_http_rpc.py
alipayplusmcp/sdk/request/__init__.py
alipayplusmcp/sdk/request/alipay_request.py
alipayplusmcp/sdk/request/customs/__init__.py
alipayplusmcp/sdk/request/customs/alipay_customs_declare_request.py
alipayplusmcp/sdk/request/customs/alipay_customs_inquire_request.py
alipayplusmcp/sdk/request/dispute/__init__.py
alipayplusmcp/sdk/request/dispute/alipay_response_escalation_request.py
ant_intl_alipayplus_mcp-1.0.1.dist-info/METADATA
ant_intl_alipayplus_mcp-1.0.1.dist-info/WHEEL
ant_intl_alipayplus_mcp-1.0.1.dist-info/entry_points.txt
ant_intl_alipayplus_mcp-1.0.1.dist-info/licenses/LICENSE
ant_intl_alipayplus_mcp-1.0.1.dist-info/RECORD
